arbre/__init__.py
arbre/__main__.py
arbre/arbre.py
arbre/cli.py
arbre-0.1.0.dist-info/METADATA
arbre-0.1.0.dist-info/WHEEL
arbre-0.1.0.dist-info/entry_points.txt
arbre-0.1.0.dist-info/top_level.txt
arbre-0.1.0.dist-info/RECORD
