Metadata-Version: 2.1
Name: arbre
Version: 0.1.0
Summary: Improved cli tree program
Home-page: https://github.com/wozacosta/arbre
Author: Wozacosta
Author-email: rabah.m.samy@gmail.com
License: MIT
Platform: UNKNOWN
Classifier: License :: OSI Approved :: MIT License
Classifier: Programming Language :: Python :: 3
Classifier: Programming Language :: Python :: 3.7
Requires-Dist: colorama
